torchseal/__init__.py
torchseal/function/__init__.py
torchseal/function/average2d.py
torchseal/function/conv2d.py
torchseal/function/cross_entropy.py
torchseal/function/linear.py
torchseal/function/mse.py
torchseal/function/relu.py
torchseal/function/sigmoid.py
torchseal/function/square.py
torchseal/function/tanh.py
torchseal/nn/__init__.py
torchseal/nn/average2d.py
torchseal/nn/conv2d.py
torchseal/nn/cross_entropy.py
torchseal/nn/linear.py
torchseal/nn/mse.py
torchseal/nn/relu.py
torchseal/nn/sigmoid.py
torchseal/nn/square.py
torchseal/nn/tanh.py
torchseal/optim/__init__.py
torchseal/optim/sgd.py
torchseal/state/__init__.py
torchseal/state/context.py
torchseal/utils/__init__.py
torchseal/utils/average2d.py
torchseal/utils/block.py
torchseal/utils/conv2d.py
torchseal/utils/handle_batch_size.py
torchseal/utils/near_zeros.py
torchseal/utils/padding.py
torchseal/utils/sparse.py
torchseal/utils/toeplitz.py
torchseal/wrapper/__init__.py
torchseal/wrapper/ckks.py
torchseal/wrapper/function.py
torchseal-0.2.0.dist-info/LICENSE
torchseal-0.2.0.dist-info/METADATA
torchseal-0.2.0.dist-info/WHEEL
torchseal-0.2.0.dist-info/top_level.txt
torchseal-0.2.0.dist-info/RECORD
