Metadata-Version: 2.1
Name: torchseal
Version: 0.2.0
Summary: PyTorch extension to enable training and testing using homomorphic encryption
Author-email: Rayhan Kinan Muhannad <rayhankinan@gmail.com>
Project-URL: Homepage, https://github.com/cnn-for-ckks/pytorch-for-tenseal
Project-URL: Issues, https://github.com/cnn-for-ckks/pytorch-for-tenseal/issues
Classifier: Programming Language :: Python :: 3
Classifier: License :: OSI Approved :: MIT License
Classifier: Operating System :: OS Independent
Requires-Python: <3.10,>=3.6
License-File: LICENSE
Requires-Dist: tenseal
Requires-Dist: numpy
Requires-Dist: torch
